cdk_lambda_bash/__init__.py
cdk_lambda_bash/py.typed
cdk_lambda_bash/_jsii/__init__.py
cdk_lambda_bash/_jsii/cdk-lambda-bash@2.0.298.jsii.tgz
cdk_lambda_bash-2.0.298.dist-info/LICENSE
cdk_lambda_bash-2.0.298.dist-info/METADATA
cdk_lambda_bash-2.0.298.dist-info/WHEEL
cdk_lambda_bash-2.0.298.dist-info/top_level.txt
cdk_lambda_bash-2.0.298.dist-info/RECORD
